steamcom/client.py
steamcom/confirmations.py
steamcom/exceptions.py
steamcom/fee_counter.py
steamcom/guard.py
steamcom/login.py
steamcom/market.py
steamcom/models.py
steamcom/utils.py
steamcom-1.2.36.dist-info/METADATA
steamcom-1.2.36.dist-info/WHEEL
steamcom-1.2.36.dist-info/licenses/LICENSE
steamcom-1.2.36.dist-info/RECORD
