Metadata-Version: 2.4
Name: steamcom
Version: 1.2.36
Summary: Python implementation of the Steam Community API
Project-URL: Homepage, https://github.com/LinarSharifullin/steamcom
Author: Linar Sharifullin
License-File: LICENSE
Classifier: License :: OSI Approved :: MIT License
Classifier: Operating System :: OS Independent
Classifier: Programming Language :: Python :: 3
Requires-Python: >=3.9
Requires-Dist: beautifulsoup4>=4.11.1
Requires-Dist: pycryptodomex>=3.14.1
Requires-Dist: requests>=2.27.1
Requires-Dist: rsa>=4.8
